firecode/TEST_NOTEBOOK.ipynb
firecode/__init__.py
firecode/__main__.py
firecode/algebra.py
firecode/ase_manipulations.py
firecode/atropisomer_module.py
firecode/automep.py
firecode/concurrent_test.py
firecode/embedder.py
firecode/embedder_options.py
firecode/embeds.py
firecode/errors.py
firecode/explode_search.py
firecode/graph_manipulations.py
firecode/hypermolecule_class.py
firecode/mep_relaxer.py
firecode/modify_settings.py
firecode/multiembed.py
firecode/numba_functions.py
firecode/operators.py
firecode/optimization_methods.py
firecode/parameters.py
firecode/pka.py
firecode/profiler.py
firecode/pt.py
firecode/quotes.json
firecode/quotes.py
firecode/reactive_atoms_classes.py
firecode/references.py
firecode/settings.py
firecode/solvents.py
firecode/standalone_optimizer.py
firecode/tests.py
firecode/torsion_module.py
firecode/units.py
firecode/utils.py
firecode/calculators/__init__.py
firecode/calculators/_ase_uma.py
firecode/calculators/_orca.py
firecode/calculators/_xtb.py
firecode/calculators/dummy_ase_calc.py
firecode/tests/C2H4.xyz
firecode-1.4.0.dist-info/licenses/LICENSE
firecode-1.4.0.dist-info/METADATA
firecode-1.4.0.dist-info/WHEEL
firecode-1.4.0.dist-info/top_level.txt
firecode-1.4.0.dist-info/RECORD
