Metadata-Version: 2.4
Name: firecode
Version: 1.4.0
Summary: Computational chemistry general purpose ensemble optimizer and molecular assemblies builder
Home-page: https://www.github.com/ntampellini/firecode
Author: Nicolò Tampellini
Author-email: nicolo.tampellini@yale.edu
Keywords: computational chemistry,ASE,transition state,xtb,AIMNET2,TBLITE
Classifier: Programming Language :: Python :: 3
Classifier: Programming Language :: Python :: 3.12
Classifier: License :: OSI Approved :: GNU Lesser General Public License v3 (LGPLv3)
Classifier: Operating System :: OS Independent
Requires-Python: >=3.12
License-File: LICENSE
Requires-Dist: numpy
Requires-Dist: scipy
Requires-Dist: matplotlib
Requires-Dist: networkx
Requires-Dist: ase
Requires-Dist: prettytable
Requires-Dist: typing-extensions
Requires-Dist: llvmlite
Requires-Dist: importlib-metadata
Requires-Dist: psutil
Requires-Dist: setuptools
Requires-Dist: rich
Requires-Dist: inquirerpy
Requires-Dist: prism-pruner
Dynamic: author
Dynamic: author-email
Dynamic: classifier
Dynamic: description
Dynamic: description-content-type
Dynamic: home-page
Dynamic: keywords
Dynamic: license-file
Dynamic: requires-dist
Dynamic: requires-python
Dynamic: summary
